trytond/modules/lims/__init__.py
trytond/modules/lims/analysis.py
trytond/modules/lims/analysis.xml
trytond/modules/lims/certification.py
trytond/modules/lims/certification.xml
trytond/modules/lims/configuration.py
trytond/modules/lims/configuration.xml
trytond/modules/lims/control_tendency.py
trytond/modules/lims/control_tendency.xml
trytond/modules/lims/department.py
trytond/modules/lims/department.xml
trytond/modules/lims/entry.py
trytond/modules/lims/entry.xml
trytond/modules/lims/formula_parser.py
trytond/modules/lims/fraction.xml
trytond/modules/lims/laboratory.py
trytond/modules/lims/laboratory.xml
trytond/modules/lims/notebook.py
trytond/modules/lims/notebook.xml
trytond/modules/lims/party.py
trytond/modules/lims/party.xml
trytond/modules/lims/planification.py
trytond/modules/lims/planification.xml
trytond/modules/lims/results_report.py
trytond/modules/lims/results_report.xml
trytond/modules/lims/sample.py
trytond/modules/lims/sample.xml
trytond/modules/lims/stock.py
trytond/modules/lims/stock.xml
trytond/modules/lims/tryton.cfg
trytond/modules/lims/uom.py
trytond/modules/lims/uom.xml
trytond/modules/lims/user.xml
trytond/modules/lims/icons/blue.svg
trytond/modules/lims/icons/concentration_level.svg
trytond/modules/lims/icons/configuration.svg
trytond/modules/lims/icons/control_means_deviations_calc.svg
trytond/modules/lims/icons/create_fraction_con.svg
trytond/modules/lims/icons/entry_board.svg
trytond/modules/lims/icons/execute_icon.svg
trytond/modules/lims/icons/generate_results_report.svg
trytond/modules/lims/icons/green.svg
trytond/modules/lims/icons/lab_icon.svg
trytond/modules/lims/icons/laboratory.svg
trytond/modules/lims/icons/laboratory_control.svg
trytond/modules/lims/icons/laboratory_reports.svg
trytond/modules/lims/icons/laboratory_results.svg
trytond/modules/lims/icons/notebook.svg
trytond/modules/lims/icons/notebook_line_all_menu.svg
trytond/modules/lims/icons/notebook_load_results_formula.svg
kalenis_lims-5.0.0.dist-info/METADATA
kalenis_lims-5.0.0.dist-info/WHEEL
kalenis_lims-5.0.0.dist-info/entry_points.txt
kalenis_lims-5.0.0.dist-info/top_level.txt
kalenis_lims-5.0.0.dist-info/RECORD
