Metadata-Version: 2.1
Name: kalenis-lims
Version: 5.0.0
Summary: Kalenis LIMS & ERP
Home-page: http://www.kalenislims.com/
Author: Kalenis
Author-email: info@kalenislims.com
License: GPL-3
Download-URL: https://bitbucket.org/kalenis/kalenislims
Platform: UNKNOWN
Classifier: Development Status :: 5 - Production/Stable
Classifier: Environment :: Plugins
Classifier: Framework :: Tryton
Classifier: Intended Audience :: Developers
Classifier: Intended Audience :: Manufacturing
Classifier: Intended Audience :: Science/Research
Classifier: Intended Audience :: Other Audience
Classifier: License :: OSI Approved :: GNU General Public License v3 or later (GPLv3+)
Classifier: Natural Language :: English
Classifier: Operating System :: OS Independent
Classifier: Programming Language :: Python :: 3.5
Classifier: Programming Language :: Python :: 3.6
Classifier: Programming Language :: Python :: 3.7
Classifier: Programming Language :: Python :: Implementation :: CPython
Classifier: Programming Language :: Python :: Implementation :: PyPy
Classifier: Topic :: Office/Business
Classifier: Topic :: Scientific/Engineering
Requires-Dist: PyPDF2
Requires-Dist: pytz
Requires-Dist: trytond (<5.1,>=5.0)
Requires-Dist: trytond-account-invoice (<5.1,>=5.0)
Requires-Dist: trytond-analytic-account (<5.1,>=5.0)
Requires-Dist: trytond-carrier (<5.1,>=5.0)
Requires-Dist: trytond-party-relationship (<5.1,>=5.0)
Requires-Dist: trytond-production (<5.1,>=5.0)
Requires-Dist: trytond-purchase (<5.1,>=5.0)
Requires-Dist: trytond-sale (<5.1,>=5.0)
Requires-Dist: trytond-stock-lot (<5.1,>=5.0)
Requires-Dist: xlrd
Requires-Dist: xlutils
